fifofile/__init__.py
fifofile/fifofile.py
fifofile-1.0.0.dist-info/LICENSE
fifofile-1.0.0.dist-info/METADATA
fifofile-1.0.0.dist-info/WHEEL
fifofile-1.0.0.dist-info/top_level.txt
fifofile-1.0.0.dist-info/RECORD
