Metadata-Version: 2.1
Name: fifofile
Version: 1.0.0
Summary: FiFoFile is a class that makes it easy to read and write lines in fifo files (named pipes)
Home-page: https://github.com/rabuchaim/fifofile
Author: Ricardo Abuchaim
Author-email: ricardoabuchaim@gmail.com
Maintainer: Ricardo Abuchaim
Maintainer-email: ricardoabuchaim@gmail.com
License: MIT
Project-URL: Issue Tracker, https://github.com/rabuchaim/fifofile/issues
Project-URL: Source code, https://github.com/rabuchaim/fifofile
Keywords: fifo,fifofile,fifo file,named,named pipes,named pipe,epoll,select,poll,polling,syslog-ng,syslog,rsyslog
Classifier: Development Status :: 5 - Production/Stable
Classifier: Topic :: Security
Classifier: Topic :: Internet
Classifier: Topic :: Scientific/Engineering
Classifier: Topic :: System :: Monitoring
Classifier: Topic :: System :: Systems Administration
Classifier: Topic :: Software Development :: Libraries
Classifier: Topic :: Software Development :: Libraries :: Python Modules
Classifier: Topic :: Utilities
Classifier: Intended Audience :: Developers
Classifier: Intended Audience :: Information Technology
Classifier: Intended Audience :: System Administrators
Classifier: Operating System :: MacOS
Classifier: Operating System :: Microsoft :: Windows :: Windows 10
Classifier: Operating System :: Microsoft :: Windows :: Windows 11
Classifier: Operating System :: Unix
Classifier: Operating System :: POSIX
Classifier: Operating System :: POSIX :: Linux
Classifier: Operating System :: POSIX :: BSD
Classifier: Operating System :: POSIX :: BSD :: FreeBSD
Classifier: Programming Language :: Python
Classifier: Programming Language :: Python :: 3.10
Classifier: Programming Language :: Python :: 3.11
Classifier: Programming Language :: Python :: 3.12
Classifier: Programming Language :: Python :: 3.13
Classifier: License :: OSI Approved :: MIT License
Requires-Python: >=3.0
License-File: LICENSE
